{
	"credit": "Made with Blockbench",
	"textures": {
		"1": "melting_point:block/smeltery",
		"2": "melting_point:block/smeltery_side",
		"3": "melting_point:block/smeltery_front_off"
	},
	"elements": [
		{
			"from": [0, 0, 0],
			"to": [16, 16, 16],
			"faces": {
				"north": {"uv": [0, 0, 16, 16], "texture": "#3"},
				"east": {"uv": [0, 0, 16, 16], "texture": "#2"},
				"south": {"uv": [0, 0, 16, 16], "texture": "#2"},
				"west": {"uv": [0, 0, 16, 16], "texture": "#2"},
				"up": {"uv": [0, 0, 16, 16], "texture": "#1"},
				"down": {"uv": [0, 0, 16, 16], "texture": "#1"}
			}
		}
	]
}